threadswitch/__init__.py
threadswitch/errors.py
threadswitch/threadswitch.py
threadswitch/utils.py
threadswitch-1.0.0.dist-info/LICENSE
threadswitch-1.0.0.dist-info/METADATA
threadswitch-1.0.0.dist-info/WHEEL
threadswitch-1.0.0.dist-info/top_level.txt
threadswitch-1.0.0.dist-info/RECORD
