Metadata-Version: 2.1
Name: threadswitch
Version: 1.0.0
Summary: "Run arbitrary tasks in contexts associated with a single thread."
Home-page: https://github.com/Kiruse/PyThreadSwitch
Author: Kiruse
Author-email: kiruse@kiruse.dev
License: MIT
Keywords: threading,asyncio,io
Platform: UNKNOWN
Requires-Python: >=3.0
